fixationmodel/__init__.py
fixationmodel-0.1.3.dist-info/DESCRIPTION.rst
fixationmodel-0.1.3.dist-info/METADATA
fixationmodel-0.1.3.dist-info/metadata.json
fixationmodel-0.1.3.dist-info/RECORD
fixationmodel-0.1.3.dist-info/top_level.txt
fixationmodel-0.1.3.dist-info/WHEEL
