Metadata-Version: 2.0
Name: fixationmodel
Version: 0.1.3
Summary: A least-squares offline method to test if tracked gaze points resemble a fixation
Home-page: https://github.com/infant-cognition-tampere/fixationmodel-py
Author: Akseli Palen
Author-email: akseli.palen@gmail.com
License: MIT
Keywords: fixation estimation eye-tracking
Platform: UNKNOWN
Classifier: Development Status :: 4 - Beta
Classifier: Intended Audience :: Developers
Classifier: Intended Audience :: Science/Research
Classifier: Topic :: Scientific/Engineering :: Mathematics
Classifier: Topic :: Scientific/Engineering :: Image Recognition
Classifier: Topic :: Scientific/Engineering :: Human Machine Interfaces
Classifier: License :: OSI Approved :: MIT License
Classifier: Programming Language :: Python :: 2
Classifier: Programming Language :: Python :: 3
Classifier: Operating System :: OS Independent
